LICENSE.txt
MANIFEST.in
README.rst
setup.cfg
setup.py
flask_error_monitor/__init__.py
flask_error_monitor/defaults.py
flask_error_monitor/exception_formatter.py
flask_error_monitor/flask_error.py
flask_error_monitor/mixins.py
flask_error_monitor/utils.py
flask_error_monitor/view.py
flask_error_monitor.egg-info/PKG-INFO
flask_error_monitor.egg-info/SOURCES.txt
flask_error_monitor.egg-info/dependency_links.txt
flask_error_monitor.egg-info/not-zip-safe
flask_error_monitor.egg-info/requires.txt
flask_error_monitor.egg-info/top_level.txt
flask_error_monitor/templates/base.html
flask_error_monitor/templates/detail.html
flask_error_monitor/templates/list.html