Metadata-Version: 2.1
Name: flask-error-monitor
Version: 0.1.1
Summary: Simple and Extensible Error Monitor framework for Flask
Home-page: https://github.com/sonus21/flask-error-monitor/
Author: sonus21
Author-email: sonunitw12@gmail.com
License: BSD-3-Clause
Keywords: Flask,error-tracker,exception-monitoring
Platform: any
Classifier: Development Status :: 5 - Production/Stable
Classifier: Environment :: Web Environment
Classifier: Intended Audience :: Developers
Classifier: License :: OSI Approved :: BSD License
Classifier: Operating System :: OS Independent
Classifier: Programming Language :: Python
Classifier: Programming Language :: Python :: 2.7
Classifier: Programming Language :: Python :: 3.5
Classifier: Programming Language :: Python :: 3.6
Classifier: Programming Language :: Python :: 3.7
Classifier: Programming Language :: Python :: 3.8
Classifier: Topic :: Software Development :: Libraries :: Python Modules
Requires-Python: >=2.7, !=3.0.*, !=3.1.*, !=3.2.*, !=3.3.*, !=3.4.*
